.gitignore
HISTORY.rst
LICENSE
MANIFEST.in
README.rst
flake.lock
flake.nix
optional_requirements.txt
requirements.txt
setup.py
docs/conf.py
docs/index.rst
docs/images/original-targetting.png
docs/images/original.png
docs/images/revised-targetting.png
docs/images/revised.png
docs/images/three-compartment-effect.png
docs/images/three-compartment.png
docs/images/two-compartment.png
docs/source/advanced.rst
docs/source/background.rst
docs/source/install.rst
docs/source/models.rst
docs/source/modules.rst
docs/source/opentiva.rst
docs/source/userguide.rst
examples/example_ke0_tpeak_method.py
examples/example_model.py
examples/example_user_infusion.py
opentiva/__init__.py
opentiva/alfentanil.py
opentiva/atracurium.py
opentiva/biometrics.py
opentiva/cisatracurium.py
opentiva/dexmedetomidine.py
opentiva/etomidate.py
opentiva/fentanyl.py
opentiva/ketamine.py
opentiva/midazolam.py
opentiva/model.py
opentiva/morphine.py
opentiva/pkpd.c
opentiva/pkpd.pyx
opentiva/propofol.py
opentiva/pump.py
opentiva/remifentanil.py
opentiva/remimazolam.py
opentiva/rocuronium.py
opentiva/sufentanil.py
opentiva/thiopental.py
opentiva/vecuronium.py
opentiva.egg-info/PKG-INFO
opentiva.egg-info/SOURCES.txt
opentiva.egg-info/dependency_links.txt
opentiva.egg-info/not-zip-safe
opentiva.egg-info/requires.txt
opentiva.egg-info/top_level.txt