Metadata-Version: 2.1
Name: opentiva
Version: 1.1.2
Summary: Simulation of target controlled infusions usingpharmacokinetic and pharmacodynamic models.
Author: James Selby
Author-email: opentiva@jpselby.co.uk
License: LICENSE
Project-URL: Documentation, https://opentiva.readthedocs.io
Project-URL: Source, https://github.com/opentiva/opentiva
Classifier: Development Status :: 5 - Production/Stable
Classifier: Intended Audience :: Healthcare Industry
Classifier: Intended Audience :: Science/Research
Classifier: License :: OSI Approved :: MIT License
Classifier: Natural Language :: English
Classifier: Operating System :: OS Independent
Classifier: Programming Language :: Python :: 3
Classifier: Programming Language :: Python :: 3.8
Classifier: Programming Language :: Python :: 3.9
Classifier: Programming Language :: Python :: Implementation :: CPython
Classifier: Programming Language :: Python :: Implementation :: PyPy
License-File: LICENSE
